[
{"division":"Dhaka","district":"Gazipur","upazila":"Gazipur Sadar","union":"","A2IReference":"division=3&district=20&upazila=163","facilityNameBengali":"শহীদ তাজউদ্দিন আহমেদ মেডিকেল কলেজ হাসপাতাল","facilityNameEnglish":"Shaheed Taj Uddin Ahmad Medical College","facilityTypeBengali":"মেডিকেল কলেজ","facilityTypeEnglish":"HEALTH_FACILITY","email":"ggazipurmc@ac.dghs.gov.bd","phone":"01711220636"},
{"division":"Dhaka","district":"Gazipur","upazila":"Kaliganj","union":"","A2IReference":"division=3&district=20&upazila=165","facilityNameBengali":"কালীগঞ্জ ইউনিয়ন উপ-স্বাস্থ্য কেন্দ্র","facilityNameEnglish":"Kaliganj Union Sub Center","facilityTypeBengali":"ইউনিয়ন উপ-স্বাস্থ্য কেন্দ্র","facilityTypeEnglish":"HEALTH_FACILITY","email":"kaliganj_singra@usc.dghs.gov.bd","phone":"01833280000"},
{"division":"Dhaka","district":"Gazipur","upazila":"Kaliganj","union":"Urban Ward No-05","A2IReference":"division=3&district=20&upazila=165","facilityNameBengali":"কালীগঞ্জ উপজেলা স্বাস্থ্য কমপ্লেক্স","facilityNameEnglish":"Kaliganj Upazila Health Complex","facilityTypeBengali":"উপজেলা স্বাস্থ্য কমপ্লেক্স","facilityTypeEnglish":"HEALTH_FACILITY","email":"kaliganj@uhfpo.dghs.gov.bd","phone":"01769957469"},
{"division":"Dhaka","district":"Gazipur","upazila":"Kaliganj","union":"Bahadursadi","A2IReference":"division=3&district=20&upazila=165","facilityNameBengali":"ধলাশাধুখান সিসি - কালিগঞ্জ","facilityNameEnglish":"Dholashadhukhan Cc","facilityTypeBengali":"কমিউনিটি ক্লিনিক","facilityTypeEnglish":"HEALTH_FACILITY","email":"cc10005330@cc.dghs.gov.bd","phone":"01913509954"},
{"division":"Dhaka","district":"Gazipur","upazila":"Kaliganj","union":"Bahadursadi","A2IReference":"division=3&district=20&upazila=165","facilityNameBengali":"খোলাপাড়া সিসি - কালিগঞ্জ","facilityNameEnglish":"Kholapara Cc","facilityTypeBengali":"কমিউনিটি ক্লিনিক","facilityTypeEnglish":"HEALTH_FACILITY","email":"cc10005331@cc.dghs.gov.bd","phone":"01822615831"},
{"division":"Dhaka","district":"Gazipur","upazila":"Kaliganj","union":"Baktarpur","A2IReference":"division=3&district=20&upazila=165","facilityNameBengali":"বেরুয়া সিসি - কালিগঞ্জ","facilityNameEnglish":"Berua Cc","facilityTypeBengali":"কমিউনিটি ক্লিনিক","facilityTypeEnglish":"HEALTH_FACILITY","email":"cc10005332@cc.dghs.gov.bd","phone":"01784398882"},
{"division":"Dhaka","district":"Gazipur","upazila":"Kaliganj","union":"Baktarpur","A2IReference":"division=3&district=20&upazila=165","facilityNameBengali":"ব্রাহ্মণগাঁও সিসি - কালিগঞ্জ","facilityNameEnglish":"Brammangaon Cc","facilityTypeBengali":"কমিউনিটি ক্লিনিক","facilityTypeEnglish":"HEALTH_FACILITY","email":"cc10005333@cc.dghs.gov.bd","phone":"01710205124"},
{"division":"Dhaka","district":"Gazipur","upazila":"Kaliganj","union":"Baktarpur","A2IReference":"division=3&district=20&upazila=165","facilityNameBengali":"ফুলদি সিসি - কালিগঞ্জ","facilityNameEnglish":"Fuldi Cc","facilityTypeBengali":"কমিউনিটি ক্লিনিক","facilityTypeEnglish":"HEALTH_FACILITY","email":"cc10005334@cc.dghs.gov.bd","phone":"01724380333"},
{"division":"Dhaka","district":"Gazipur","upazila":"Kaliganj","union":"Baktarpur","A2IReference":"division=3&district=20&upazila=165","facilityNameBengali":"মাজুখান সিসি - কালিগঞ্জ","facilityNameEnglish":"Majhukhan Cc","facilityTypeBengali":"কমিউনিটি ক্লিনিক","facilityTypeEnglish":"HEALTH_FACILITY","email":"cc10005335@cc.dghs.gov.bd","phone":"01710829696"},
{"division":"Dhaka","district":"Gazipur","upazila":"Kaliganj","union":"Baktarpur","A2IReference":"division=3&district=20&upazila=165","facilityNameBengali":"মোহানি সিসি - কালিগঞ্জ","facilityNameEnglish":"Mohani Cc","facilityTypeBengali":"কমিউনিটি ক্লিনিক","facilityTypeEnglish":"HEALTH_FACILITY","email":"cc10005336@cc.dghs.gov.bd","phone":"01818748812"},
{"division":"Dhaka","district":"Gazipur","upazila":"Kaliganj","union":"Baktarpur","A2IReference":"division=3&district=20&upazila=165","facilityNameBengali":"ভাটিরা সিসি - কালিগঞ্জ","facilityNameEnglish":"Vatira Cc","facilityTypeBengali":"কমিউনিটি ক্লিনিক","facilityTypeEnglish":"HEALTH_FACILITY","email":"cc10005337@cc.dghs.gov.bd","phone":"01820534056"},
{"division":"Dhaka","district":"Gazipur","upazila":"Kaliganj","union":"Jamalpur","A2IReference":"division=3&district=20&upazila=165","facilityNameBengali":"ছাইলাদি সিসি - কালিগঞ্জ","facilityNameEnglish":"Chhailadi Cc","facilityTypeBengali":"কমিউনিটি ক্লিনিক","facilityTypeEnglish":"HEALTH_FACILITY","email":"cc10005338@cc.dghs.gov.bd","phone":"01720901210"},
{"division":"Dhaka","district":"Gazipur","upazila":"Kaliganj","union":"Jamalpur","A2IReference":"division=3&district=20&upazila=165","facilityNameBengali":"জামালপুর সিসি - কালিগঞ্জ","facilityNameEnglish":"Jamalpur Cc","facilityTypeBengali":"কমিউনিটি ক্লিনিক","facilityTypeEnglish":"HEALTH_FACILITY","email":"cc10005339@cc.dghs.gov.bd","phone":"01710434146"},
{"division":"Dhaka","district":"Gazipur","upazila":"Kaliganj","union":"Jamalpur","A2IReference":"division=3&district=20&upazila=165","facilityNameBengali":"কাপাইস সিসি - কালিগঞ্জ","facilityNameEnglish":"Kapais Cc","facilityTypeBengali":"কমিউনিটি ক্লিনিক","facilityTypeEnglish":"HEALTH_FACILITY","email":"cc10005340@cc.dghs.gov.bd","phone":"01715109218"},
{"division":"Dhaka","district":"Gazipur","upazila":"Kaliganj","union":"Jangalia","A2IReference":"division=3&district=20&upazila=165","facilityNameBengali":"ছাতিয়ানি সিসি - কালিগঞ্জ","facilityNameEnglish":"Chhatiyani Cc ","facilityTypeBengali":"কমিউনিটি ক্লিনিক","facilityTypeEnglish":"HEALTH_FACILITY","email":"cc10005341@cc.dghs.gov.bd","phone":"01916739950"},
{"division":"Dhaka","district":"Gazipur","upazila":"Kaliganj","union":"Jangalia","A2IReference":"division=3&district=20&upazila=165","facilityNameBengali":"ডুবরিয়া সিসি - কালিগঞ্জ","facilityNameEnglish":"Dubriya Cc","facilityTypeBengali":"কমিউনিটি ক্লিনিক","facilityTypeEnglish":"HEALTH_FACILITY","email":"cc10005342@cc.dghs.gov.bd","phone":"01912355502"},
{"division":"Dhaka","district":"Gazipur","upazila":"Kaliganj","union":"Jangalia","A2IReference":"division=3&district=20&upazila=165","facilityNameBengali":"জাঙ্গালিয়া সিসি - কালিগঞ্জ","facilityNameEnglish":"Jangaliya Cc","facilityTypeBengali":"কমিউনিটি ক্লিনিক","facilityTypeEnglish":"HEALTH_FACILITY","email":"cc10005343@cc.dghs.gov.bd","phone":"01723651943"},
{"division":"Dhaka","district":"Gazipur","upazila":"Kaliganj","union":"","A2IReference":"division=3&district=20&upazila=165","facilityNameBengali":"ছাইতেরপারা সিসি - কালিগঞ্জ","facilityNameEnglish":"Chaiterpara CC","facilityTypeBengali":"কমিউনিটি ক্লিনিক","facilityTypeEnglish":"HEALTH_FACILITY","email":"cc10005344@cc.dghs.gov.bd","phone":"01746795168"},
{"division":"Dhaka","district":"Gazipur","upazila":"Kaliganj","union":"Bahadursadi","A2IReference":"division=3&district=20&upazila=165","facilityNameBengali":"ছান্দাইয়া সিসি - কালিগঞ্জ","facilityNameEnglish":"Chandaiya CC","facilityTypeBengali":"কমিউনিটি ক্লিনিক","facilityTypeEnglish":"HEALTH_FACILITY","email":"cc10005345@cc.dghs.gov.bd","phone":"01713582076"},
{"division":"Dhaka","district":"Gazipur","upazila":"Kaliganj","union":"","A2IReference":"division=3&district=20&upazila=165","facilityNameBengali":"দেওপারা সিসি - কালিগঞ্জ","facilityNameEnglish":"Deopara Cc ","facilityTypeBengali":"কমিউনিটি ক্লিনিক","facilityTypeEnglish":"HEALTH_FACILITY","email":"cc10005346@cc.dghs.gov.bd","phone":"01945127140"},
{"division":"Dhaka","district":"Gazipur","upazila":"Kaliganj","union":"Bahadursadi","A2IReference":"division=3&district=20&upazila=165","facilityNameBengali":"ডুব্বাতি সিসি - কালিগঞ্জ","facilityNameEnglish":"Dubbati CC ","facilityTypeBengali":"কমিউনিটি ক্লিনিক","facilityTypeEnglish":"HEALTH_FACILITY","email":"cc10005347@cc.dghs.gov.bd","phone":"01735071148"},
{"division":"Dhaka","district":"Gazipur","upazila":"Kaliganj","union":"","A2IReference":"division=3&district=20&upazila=165","facilityNameBengali":"কুমারটেক সিসি - কালিগঞ্জ","facilityNameEnglish":"Kumartek Cc","facilityTypeBengali":"কমিউনিটি ক্লিনিক","facilityTypeEnglish":"HEALTH_FACILITY","email":"cc10005348@cc.dghs.gov.bd","phone":"01721524414"},
{"division":"Dhaka","district":"Gazipur","upazila":"Kaliganj","union":"","A2IReference":"division=3&district=20&upazila=165","facilityNameBengali":"উত্তারগাঁও সিসি - কালিগঞ্জ","facilityNameEnglish":"Uttargaon Cc ","facilityTypeBengali":"কমিউনিটি ক্লিনিক","facilityTypeEnglish":"HEALTH_FACILITY","email":"cc10005349@cc.dghs.gov.bd","phone":"01723010799"},
{"division":"Dhaka","district":"Gazipur","upazila":"Kaliganj","union":"Moktarpur","A2IReference":"division=3&district=20&upazila=165","facilityNameBengali":"বাঘুন সিসি - কালিগঞ্জ","facilityNameEnglish":"Baghun Cc","facilityTypeBengali":"কমিউনিটি ক্লিনিক","facilityTypeEnglish":"HEALTH_FACILITY","email":"cc10005350@cc.dghs.gov.bd","phone":"01757109313"},
{"division":"Dhaka","district":"Gazipur","upazila":"Kaliganj","union":"Moktarpur","A2IReference":"division=3&district=20&upazila=165","facilityNameBengali":"বারাগাঁও সিসি - কালিগঞ্জ","facilityNameEnglish":"Baragaon Cc","facilityTypeBengali":"কমিউনিটি ক্লিনিক","facilityTypeEnglish":"HEALTH_FACILITY","email":"cc10005351@cc.dghs.gov.bd","phone":"01726452402"},
{"division":"Dhaka","district":"Gazipur","upazila":"Kaliganj","union":"Moktarpur","A2IReference":"division=3&district=20&upazila=165","facilityNameBengali":"ধানপুর সিসি - কালিগঞ্জ","facilityNameEnglish":"Dhanpur Cc ","facilityTypeBengali":"কমিউনিটি ক্লিনিক","facilityTypeEnglish":"HEALTH_FACILITY","email":"cc10005352@cc.dghs.gov.bd","phone":"01719691215"},
{"division":"Dhaka","district":"Gazipur","upazila":"Kaliganj","union":"Moktarpur","A2IReference":"division=3&district=20&upazila=165","facilityNameBengali":"রাথুরা সিসি - কালিগঞ্জ","facilityNameEnglish":"Rathura Cc","facilityTypeBengali":"কমিউনিটি ক্লিনিক","facilityTypeEnglish":"HEALTH_FACILITY","email":"cc10005353@cc.dghs.gov.bd","phone":"01718433397"},
{"division":"Dhaka","district":"Gazipur","upazila":"Kaliganj","union":"Moktarpur","A2IReference":"division=3&district=20&upazila=165","facilityNameBengali":"শিংলাব সিসি - কালিগঞ্জ","facilityNameEnglish":"Shinglab Cc","facilityTypeBengali":"কমিউনিটি ক্লিনিক","facilityTypeEnglish":"HEALTH_FACILITY","email":"cc10005354@cc.dghs.gov.bd","phone":"01716550722"},
{"division":"Dhaka","district":"Gazipur","upazila":"Kaliganj","union":"Tumulia","A2IReference":"division=3&district=20&upazila=165","facilityNameBengali":"বোয়ালি সিসি - কালিগঞ্জ","facilityNameEnglish":"Boali Cc","facilityTypeBengali":"কমিউনিটি ক্লিনিক","facilityTypeEnglish":"HEALTH_FACILITY","email":"cc10005355@cc.dghs.gov.bd","phone":"01918108510"},
{"division":"Dhaka","district":"Gazipur","upazila":"Kaliganj","union":"Tumulia","A2IReference":"division=3&district=20&upazila=165","facilityNameBengali":"সাউথ সম সিসি - কালিগঞ্জ","facilityNameEnglish":"South Som Cc","facilityTypeBengali":"কমিউনিটি ক্লিনিক","facilityTypeEnglish":"HEALTH_FACILITY","email":"cc10005356@cc.dghs.gov.bd","phone":"01756862098"},
{"division":"Dhaka","district":"Gazipur","upazila":"Kaliganj","union":"","A2IReference":"division=3&district=20&upazila=165","facilityNameBengali":"বাহাদুরশাদী ইউনিয়ন সেন্টার","facilityNameEnglish":"Bahadurshadi Union Centre ","facilityTypeBengali":"ইউনিয়্ন স্বাস্থ্য কেন্দ্র","facilityTypeEnglish":"HEALTH_FACILITY","email":"u10015046@union.dghs.gov.bd","phone":""},
{"division":"Dhaka","district":"Gazipur","upazila":"Kaliganj","union":"","A2IReference":"division=3&district=20&upazila=165","facilityNameBengali":"বক্তারপুর ইউনিয়ন সেন্টার","facilityNameEnglish":"Baktarpur Union Centre ","facilityTypeBengali":"ইউনিয়্ন স্বাস্থ্য কেন্দ্র","facilityTypeEnglish":"HEALTH_FACILITY","email":"u10015047@union.dghs.gov.bd","phone":""},
{"division":"Dhaka","district":"Gazipur","upazila":"Kaliganj","union":"","A2IReference":"division=3&district=20&upazila=165","facilityNameBengali":"জামালপুর ইউনিয়ন সেন্টার","facilityNameEnglish":"Jamalpur Union Centre","facilityTypeBengali":"ইউনিয়্ন স্বাস্থ্য কেন্দ্র","facilityTypeEnglish":"HEALTH_FACILITY","email":"u10015048@union.dghs.gov.bd","phone":""},
{"division":"Dhaka","district":"Gazipur","upazila":"Kaliganj","union":"","A2IReference":"division=3&district=20&upazila=165","facilityNameBengali":"জাঙ্গালিয়া ইউনিয়ন সেন্টার","facilityNameEnglish":"Jangalia Union Centre","facilityTypeBengali":"ইউনিয়্ন স্বাস্থ্য কেন্দ্র","facilityTypeEnglish":"HEALTH_FACILITY","email":"u10015049@union.dghs.gov.bd","phone":""},
{"division":"Dhaka","district":"Gazipur","upazila":"Kaliganj","union":"","A2IReference":"division=3&district=20&upazila=165","facilityNameBengali":"মোক্তারপুর ইউনিয়ন সেন্টার","facilityNameEnglish":"Moktarpur Union Centre","facilityTypeBengali":"ইউনিয়্ন স্বাস্থ্য কেন্দ্র","facilityTypeEnglish":"HEALTH_FACILITY","email":"u10015050@union.dghs.gov.bd","phone":""},
{"division":"Dhaka","district":"Gazipur","upazila":"Kaliganj","union":"","A2IReference":"division=3&district=20&upazila=165","facilityNameBengali":"নাগরি ইউনিয়ন সেন্টার","facilityNameEnglish":"Nagri Union Centre","facilityTypeBengali":"ইউনিয়্ন স্বাস্থ্য কেন্দ্র","facilityTypeEnglish":"HEALTH_FACILITY","email":"u10015051@union.dghs.gov.bd","phone":""},
{"division":"Dhaka","district":"Gazipur","upazila":"Kaliganj","union":"","A2IReference":"division=3&district=20&upazila=165","facilityNameBengali":"তুমুলিয়া ইউনিয়ন সেন্টার","facilityNameEnglish":"Tumulia Union Centre","facilityTypeBengali":"ইউনিয়্ন স্বাস্থ্য কেন্দ্র","facilityTypeEnglish":"HEALTH_FACILITY","email":"u10015052@union.dghs.gov.bd","phone":""},
{"division":"Dhaka","district":"Gazipur","upazila":"Kaliganj","union":"Nagari","A2IReference":"division=3&district=20&upazila=165","facilityNameBengali":"রয়েন সিসি - কালিগঞ্জ","facilityNameEnglish":"Royen CC- Kaligonj","facilityTypeBengali":"কমিউনিটি ক্লিনিক","facilityTypeEnglish":"HEALTH_FACILITY","email":"cc10018828@cc.dghs.gov.bd","phone":"01723133608"},
{"division":"Dhaka","district":"Gazipur","upazila":"Kaliganj","union":"Nagari","A2IReference":"division=3&district=20&upazila=165","facilityNameBengali":"পারাবারথা সিসি - কালিগঞ্জ","facilityNameEnglish":"Parabartha CC- Kaligonj","facilityTypeBengali":"কমিউনিটি ক্লিনিক","facilityTypeEnglish":"HEALTH_FACILITY","email":"cc10018829@cc.dghs.gov.bd","phone":"01760820154"},
{"division":"Dhaka","district":"Gazipur","upazila":"Kaliganj","union":"","A2IReference":"division=3&district=20&upazila=165","facilityNameBengali":"বাংলাদেশ রেড ক্রিসেন্ট সোসাইটি - কালিগঞ্জ","facilityNameEnglish":"Bangladesh Red Crescent Society-Kaliganj","facilityTypeBengali":"এনজিও হাসপাতাল / ক্লিনিক","facilityTypeEnglish":"HEALTH_FACILITY","email":"","phone":"01735064458"},
{"division":"Dhaka","district":"Gazipur","upazila":"Kaliganj","union":"Moktarpur","A2IReference":"division=3&district=20&upazila=165","facilityNameBengali":"বাংলাদেশ রেড ক্রিসেন্ট সোসাইটি - ২ কালিগঞ্জ","facilityNameEnglish":"Bangladesh Red Crescent Society-2 Kaliganj","facilityTypeBengali":"এনজিও হাসপাতাল / ক্লিনিক","facilityTypeEnglish":"HEALTH_FACILITY","email":"","phone":"01725548512"},
{"division":"Dhaka","district":"Gazipur","upazila":"Kaliganj","union":"","A2IReference":"division=3&district=20&upazila=165","facilityNameBengali":"বাংলাদেশ রেড ক্রিসেন্ট সোসাইটি -৩ কালিগঞ্জ","facilityNameEnglish":"Bangladesh Red Crescent Society-3 Kaliganj","facilityTypeBengali":"এনজিও হাসপাতাল / ক্লিনিক","facilityTypeEnglish":"HEALTH_FACILITY","email":"","phone":"01734467901"},
{"division":"Dhaka","district":"Gazipur","upazila":"Kaliganj","union":"","A2IReference":"division=3&district=20&upazila=165","facilityNameBengali":"ব্রাক (বিএইচপি) - কালিগঞ্জ","facilityNameEnglish":"BRAC (BHP) -Kaliganj","facilityTypeBengali":"এনজিও হাসপাতাল / ক্লিনিক","facilityTypeEnglish":"HEALTH_FACILITY","email":"","phone":"01710614466"},
{"division":"Dhaka","district":"Gazipur","upazila":"Kaliganj","union":"","A2IReference":"division=3&district=20&upazila=165","facilityNameBengali":"মেরি স্টোপস - কালিগঞ্জ","facilityNameEnglish":"Marie Stops-Kaliganj","facilityTypeBengali":"এনজিও হাসপাতাল / ক্লিনিক","facilityTypeEnglish":"HEALTH_FACILITY","email":"","phone":""},
{"division":"Dhaka","district":"Gazipur","upazila":"Kaliganj","union":"Tumulia","A2IReference":"division=3&district=20&upazila=165","facilityNameBengali":"সেন্ট মেরিস কাথলিক মাদার অ্যান্ড চাইল্ড হেলথ সেন্টার - কালিগঞ্জ","facilityNameEnglish":"Saint marys Catholic Mother and Child Health center-Kaliganj","facilityTypeBengali":"বেসরকারী হাসপাতাল / ক্লিনিক","facilityTypeEnglish":"HEALTH_FACILITY","email":"","phone":"01715374832"},
{"division":"Dhaka","district":"Gazipur","upazila":"Kaliganj","union":"Nagari","A2IReference":"division=3&district=20&upazila=165","facilityNameBengali":"এসটি আন্থনি মাদার অ্যান্ড চাইল্ড হেলথ কেয়ার - কালিগঞ্জ","facilityNameEnglish":"St. Anthony Mother and Child Health Care-Kaliganj","facilityTypeBengali":"বেসরকারী হাসপাতাল / ক্লিনিক","facilityTypeEnglish":"HEALTH_FACILITY","email":"","phone":"01715374832"},
{"division":"Dhaka","district":"Gazipur","upazila":"Kaliganj","union":"","A2IReference":"division=3&district=20&upazila=165","facilityNameBengali":"কালিগঞ্জ সেন্টার হসপিটাল - কালিগঞ্জ","facilityNameEnglish":"Kaliganj Central Hospital-kalioganj","facilityTypeBengali":"বেসরকারী হাসপাতাল / ক্লিনিক","facilityTypeEnglish":"HEALTH_FACILITY","email":"","phone":"01720025298"},
{"division":"Dhaka","district":"Gazipur","upazila":"Kaliganj","union":"","A2IReference":"division=3&district=20&upazila=165","facilityNameBengali":"জামিল আই জেনারেল হসপিটাল - কালিগঞ্জ","facilityNameEnglish":"Jamil Eye General Hospital-kalioganj","facilityTypeBengali":"বেসরকারী হাসপাতাল / ক্লিনিক","facilityTypeEnglish":"HEALTH_FACILITY","email":"","phone":"01711974635"},
{"division":"Dhaka","district":"Gazipur","upazila":"Kaliganj","union":"Jangalia","A2IReference":"division=3&district=20&upazila=165","facilityNameBengali":"নরুন সিসি - কালিগঞ্জ","facilityNameEnglish":"Norun CC - Kaliganj","facilityTypeBengali":"কমিউনিটি ক্লিনিক","facilityTypeEnglish":"HEALTH_FACILITY","email":"cc10022028@cc.dghs.gov.bd","phone":""},
{"division":"Dhaka","district":"Gazipur","upazila":"Kaliganj","union":"","A2IReference":"division=3&district=20&upazila=165","facilityNameBengali":"উপজেলা ফ্যামিলি ওয়েলফেয়ার অফিস - কালিগঞ্জ গাজীপুর.","facilityNameEnglish":"Upazila family welfare office","facilityTypeBengali":"ইউনিয়ন স্বাস্থ্য ও পরিবার কল্যাণ কেন্দ্র","facilityTypeEnglish":"HEALTH_FACILITY","email":"sanjida.ealy@gmail.com","phone":"01970107020"},
{"division":"Dhaka","district":"Gazipur","upazila":"Kaliganj","union":"Urban Ward No-09","A2IReference":"division=3&district=20&upazila=165","facilityNameBengali":"উপজেলা ফ্যামিলি ওয়েলফেয়ার সদর ক্লিনিক কালিগঞ্জ গাজীপুর.","facilityNameEnglish":"Upazila family welfare sadar clinic","facilityTypeBengali":"ইউনিয়ন স্বাস্থ্য ও পরিবার কল্যাণ কেন্দ্র","facilityTypeEnglish":"HEALTH_FACILITY","email":"sanjida.ealy@gmail.com","phone":"01970107020"},
{"division":"Dhaka","district":"Gazipur","upazila":"Kaliganj","union":"Bahadursadi","A2IReference":"division=3&district=20&upazila=165","facilityNameBengali":"ইউনিয়ন হেলথ অ্যান্ড ফ্যামিলি ওয়েলফেয়ার সেন্টার (ইউএইচ অ্যান্ড এফডবলিওসি) বাহাদুরশাদী কালিগঞ্জ গাজীপুর.","facilityNameEnglish":"UH & FWC Bahadursad","facilityTypeBengali":"ইউনিয়ন স্বাস্থ্য ও পরিবার কল্যাণ কেন্দ্র","facilityTypeEnglish":"HEALTH_FACILITY","email":"sanjida.ealy@gmail.com","phone":"01970107020"},
{"division":"Dhaka","district":"Gazipur","upazila":"Kaliganj","union":"Jamalpur","A2IReference":"division=3&district=20&upazila=165","facilityNameBengali":"ইউনিয়ন হেলথ অ্যান্ড ফ্যামিলি ওয়েলফেয়ার সেন্টার (এউএইচ অ্যান্ড এফডবলিওসি) জামালপুর কালিগঞ্জ গাজীপুর.","facilityNameEnglish":"UH & FWC Jamalpur","facilityTypeBengali":"ইউনিয়ন স্বাস্থ্য ও পরিবার কল্যাণ কেন্দ্র","facilityTypeEnglish":"HEALTH_FACILITY","email":"sanjida.ealy@gmail.com","phone":"01970107020"},
{"division":"Dhaka","district":"Gazipur","upazila":"Kaliganj","union":"Baktarpur","A2IReference":"division=3&district=20&upazila=165","facilityNameBengali":"ইউনিয়ন হেলথ অ্যান্ড ফ্যামিলি ওয়েলফেয়ার সেন্টার (এউএইচ অ্যান্ড এফডবলিওসি) বক্তারপুর কালিগঞ্জ গাজীপুর.","facilityNameEnglish":"UH & FWC Bakterpur","facilityTypeBengali":"ইউনিয়ন স্বাস্থ্য ও পরিবার কল্যাণ কেন্দ্র","facilityTypeEnglish":"HEALTH_FACILITY","email":"sanjida.ealy@gmail.com","phone":"01970107020"},
{"division":"Dhaka","district":"Gazipur","upazila":"Kaliganj","union":"Moktarpur","A2IReference":"division=3&district=20&upazila=165","facilityNameBengali":"ইউনিয়ন হেলথ অ্যান্ড ফ্যামিলি ওয়েলফেয়ার সেন্টার (এউএইচ অ্যান্ড এফডবলিওসি) মক্তারপুর কালিগঞ্জ গাজীপুর.","facilityNameEnglish":"UH & FWC makterpur","facilityTypeBengali":"ইউনিয়ন স্বাস্থ্য ও পরিবার কল্যাণ কেন্দ্র","facilityTypeEnglish":"HEALTH_FACILITY","email":"sanjida.ealy@gmail.com","phone":"01970107020"},
{"division":"Dhaka","district":"Gazipur","upazila":"Kaliganj","union":"Jangalia","A2IReference":"division=3&district=20&upazila=165","facilityNameBengali":"ইউনিয়ন হেলথ অ্যান্ড ফ্যামিলি ওয়েলফেয়ার সেন্টার (এউএইচ অ্যান্ড এফডবলিওসি) জাঙ্গালিয়া কালিগঞ্জ গাজীপুর.","facilityNameEnglish":"UH & FWC Jangalia","facilityTypeBengali":"ইউনিয়ন স্বাস্থ্য ও পরিবার কল্যাণ কেন্দ্র","facilityTypeEnglish":"HEALTH_FACILITY","email":"sanjida.ealy@gmail.com","phone":"01970107020"},
{"division":"Dhaka","district":"Gazipur","upazila":"Kaliganj","union":"Tumulia","A2IReference":"division=3&district=20&upazila=165","facilityNameBengali":"ইউনিয়ন হেলথ অ্যান্ড ফ্যামিলি ওয়েলফেয়ার সেন্টার (এউএইচ অ্যান্ড এফডবলিওসি) তুমুলিয়া কালিগঞ্জ গাজীপুর.","facilityNameEnglish":"UH & FWC Tumolia","facilityTypeBengali":"ইউনিয়ন স্বাস্থ্য ও পরিবার কল্যাণ কেন্দ্র","facilityTypeEnglish":"HEALTH_FACILITY","email":"","phone":"01970107020"},
{"division":"Dhaka","district":"Gazipur","upazila":"Kaliganj","union":"Baktarpur","A2IReference":"division=3&district=20&upazila=165","facilityNameBengali":"খইকরা সিসি - কালিগঞ্জ","facilityNameEnglish":"Khoikora CC - Kaliganj","facilityTypeBengali":"কমিউনিটি ক্লিনিক","facilityTypeEnglish":"HEALTH_FACILITY","email":"cc10024556@cc.dghs.gov.bd","phone":""},
{"division":"Dhaka","district":"Gazipur","upazila":"Kaliganj","union":"","A2IReference":"division=3&district=20&upazila=165","facilityNameBengali":"কালিগঞ্জ (জিপি) মুন","facilityNameEnglish":"Kaliganj (GP) Mun.","facilityTypeBengali":"উপজেলা পর্যায়ের অফিস","facilityTypeEnglish":"HEALTH_FACILITY","email":"","phone":""},
{"division":"Dhaka","district":"Narsingdi","upazila":"Narsingdi","union":"Urban Ward No-04","A2IReference":"division=3&district=29&upazila=229","facilityNameBengali":"আল্গি (মাধাব্দি) ইউনিয়ন উপ-স্বাস্থ্য কেন্দ্র","facilityNameEnglish":"Algi(madhabdi) Union Sub Center","facilityTypeBengali":"ইউনিয়ন উপ-স্বাস্থ্য কেন্দ্র","facilityTypeEnglish":"HEALTH_FACILITY","email":"algi_madhabdi@usc.dghs.gov.bd","phone":""},
{"division":"Dhaka","district":"Narsingdi","upazila":"Narsingdi","union":"Amdia","A2IReference":"division=3&district=29&upazila=229","facilityNameBengali":"আমদিয়া উপ-স্বাস্থ্য কেন্দ্র","facilityNameEnglish":"Amdia Union Sub Center","facilityTypeBengali":"ইউনিয়ন উপ-স্বাস্থ্য কেন্দ্র","facilityTypeEnglish":"HEALTH_FACILITY","email":"amdia@usc.dghs.gov.bd","phone":""},
{"division":"Dhaka","district":"Narsingdi","upazila":"Narsingdi","union":"","A2IReference":"division=3&district=29&upazila=229","facilityNameBengali":"ভাগিরাথপুর ইউনিয়ন উপ-স্বাস্থ্য কেন্দ্র","facilityNameEnglish":"Bhagirathpur Union Sub Center","facilityTypeBengali":"ইউনিয়ন উপ-স্বাস্থ্য কেন্দ্র","facilityTypeEnglish":"HEALTH_FACILITY","email":"bhagirathpur@usc.dghs.gov.bd","phone":""},
{"division":"Dhaka","district":"Narsingdi","upazila":"Narsingdi","union":"Hajipur","A2IReference":"division=3&district=29&upazila=229","facilityNameBengali":"ভাটপারা ইউনিয়ন উপ-স্বাস্থ্য কেন্দ্র","facilityNameEnglish":"Bhatpara Union Sub Center","facilityTypeBengali":"ইউনিয়ন উপ-স্বাস্থ্য কেন্দ্র","facilityTypeEnglish":"HEALTH_FACILITY","email":"bhatpara@usc.dghs.gov.bd","phone":""},
{"division":"Dhaka","district":"Narsingdi","upazila":"Narsingdi","union":"Karimpur","A2IReference":"division=3&district=29&upazila=229","facilityNameBengali":"করিমপুর ইউনিয়ন উপ-স্বাস্থ্য কেন্দ্র","facilityNameEnglish":"Karimpur Union Sub Center","facilityTypeBengali":"ইউনিয়ন উপ-স্বাস্থ্য কেন্দ্র","facilityTypeEnglish":"HEALTH_FACILITY","email":"karimpur@usc.dghs.gov.bd","phone":""},
{"division":"Dhaka","district":"Narsingdi","upazila":"Narsingdi","union":"","A2IReference":"division=3&district=29&upazila=229","facilityNameBengali":"নরসিংদী সদর ইউনিয়ন উপ-স্বাস্থ্য কেন্দ্র","facilityNameEnglish":"Narsingdi Sadar Union Sub Center","facilityTypeBengali":"ইউনিয়ন উপ-স্বাস্থ্য কেন্দ্র","facilityTypeEnglish":"HEALTH_FACILITY","email":"narsingdisadar@usc.dghs.gov.bd","phone":""},
{"division":"Dhaka","district":"Narsingdi","upazila":"Narsingdi","union":"","A2IReference":"division=3&district=29&upazila=229","facilityNameBengali":"নরসিংদী (সদর) উপজেলা স্বাস্থ্য অফিস","facilityNameEnglish":"Narsingdi (sadar) Upazila Health Office","facilityTypeBengali":"উপজেলা পর্যায়ের অফিস","facilityTypeEnglish":"HEALTH_FACILITY","email":"narsingdisadar@uhfpo.dghs.gov.bd","phone":"01712221651"},
{"division":"Dhaka","district":"Narsingdi","upazila":"Narsingdi","union":"Urban Ward No-01 (narsingdi)","A2IReference":"division=3&district=29&upazila=229","facilityNameBengali":"নরসিংদী সিভিল সার্জন অফিস","facilityNameEnglish":"Narsingdi Civil Surgeon Office","facilityTypeBengali":"জেলা পর্যায়ের অফিস","facilityTypeEnglish":"HEALTH_FACILITY","email":"norshingdi@cs.dghs.gov.bd","phone":"01797000888"},
{"division":"Dhaka","district":"Narsingdi","upazila":"Narsingdi","union":"","A2IReference":"division=3&district=29&upazila=229","facilityNameBengali":"নরসিংদী জেলা হসপিটাল","facilityNameEnglish":"Narsingdi District Hospital","facilityTypeBengali":"জেলা হাসপাতাল","facilityTypeEnglish":"HEALTH_FACILITY","email":"narsingdi@hospi.dghs.gov.bd","phone":"01797000888"},
{"division":"Dhaka","district":"Narsingdi","upazila":"Narsingdi","union":"Urban Ward No-01 (narsingdi)","A2IReference":"division=3&district=29&upazila=229","facilityNameBengali":"নরসিংদী ১০০ বেড জেলা হসপিটাল","facilityNameEnglish":"Narsingdi 100 Bed Zilla Hospital","facilityTypeBengali":"জেলা হাসপাতাল","facilityTypeEnglish":"HEALTH_FACILITY","email":"n100b@hospi.dghs.gov.bd","phone":"01730324787"},
{"division":"Dhaka","district":"Narsingdi","upazila":"Narsingdi","union":"Alokbali","A2IReference":"division=3&district=29&upazila=229","facilityNameBengali":"চরমাধবপুর (বাখারনগর) সিসি - নরসিংদী সদর","facilityNameEnglish":"Charmadhabpur(bakharnagar) Cc - Narsingdi Sadar","facilityTypeBengali":"কমিউনিটি ক্লিনিক","facilityTypeEnglish":"HEALTH_FACILITY","email":"cc10006853@cc.dghs.gov.bd","phone":"01749464912"},
{"division":"Dhaka","district":"Narsingdi","upazila":"Narsingdi","union":"Alokbali","A2IReference":"division=3&district=29&upazila=229","facilityNameBengali":"খোদাদিলা সিসি – নরসিংদী সদর","facilityNameEnglish":"Khodadila Cc - Narsingdi Sadar","facilityTypeBengali":"কমিউনিটি ক্লিনিক","facilityTypeEnglish":"HEALTH_FACILITY","email":"cc10006854@cc.dghs.gov.bd","phone":""},
{"division":"Dhaka","district":"Narsingdi","upazila":"Narsingdi","union":"Amdia","A2IReference":"division=3&district=29&upazila=229","facilityNameBengali":"বেলাব (ভাইয়ুম) সিসি - নরসিংদী সদর","facilityNameEnglish":"Belab (bhaiyum) Cc - Narsingdi Sadar","facilityTypeBengali":"কমিউনিটি ক্লিনিক","facilityTypeEnglish":"HEALTH_FACILITY","email":"cc10006855@cc.dghs.gov.bd","phone":"01731603510"},
{"division":"Dhaka","district":"Narsingdi","upazila":"Narsingdi","union":"Amdia","A2IReference":"division=3&district=29&upazila=229","facilityNameBengali":"গলাদি সিসি - নরসিংদী সদর","facilityNameEnglish":"Goaldi Cc - Narsingdi Sadar","facilityTypeBengali":"কমিউনিটি ক্লিনিক","facilityTypeEnglish":"HEALTH_FACILITY","email":"cc10006856@cc.dghs.gov.bd","phone":"01920561874"},
{"division":"Dhaka","district":"Narsingdi","upazila":"Narsingdi","union":"Amdia","A2IReference":"division=3&district=29&upazila=229","facilityNameBengali":"পাকুরিয়া সিসি - নরসিংদী সদর","facilityNameEnglish":"Pakuriya Cc - Narsingdi Sadar","facilityTypeBengali":"কমিউনিটি ক্লিনিক","facilityTypeEnglish":"HEALTH_FACILITY","email":"cc10006857@cc.dghs.gov.bd","phone":"01756042732"},
{"division":"Dhaka","district":"Narsingdi","upazila":"Narsingdi","union":"Char Dighaldi","A2IReference":"division=3&district=29&upazila=229","facilityNameBengali":"কালিকাপুর সিসি - নরসিংদী সদর","facilityNameEnglish":"Kalikapur Cc - Narsingdi Sadar","facilityTypeBengali":"কমিউনিটি ক্লিনিক","facilityTypeEnglish":"HEALTH_FACILITY","email":"cc10006858@cc.dghs.gov.bd","phone":"01814971429"},
{"division":"Dhaka","district":"Narsingdi","upazila":"Narsingdi","union":"Chinishpur","A2IReference":"division=3&district=29&upazila=229","facilityNameBengali":"চিনিসপুর সিসি - নরসিংদী সদর","facilityNameEnglish":"Chinishpur Cc - Narsingdi Sadar","facilityTypeBengali":"কমিউনিটি ক্লিনিক","facilityTypeEnglish":"HEALTH_FACILITY","email":"cc10006859@cc.dghs.gov.bd","phone":"01814760020"},
{"division":"Dhaka","district":"Narsingdi","upazila":"Narsingdi","union":"Chinishpur","A2IReference":"division=3&district=29&upazila=229","facilityNameBengali":"ঘোরাদিয়া সিসি - নরসিংদী সদর","facilityNameEnglish":"Ghoradiya Cc - Narsingdi Sadar","facilityTypeBengali":"কমিউনিটি ক্লিনিক","facilityTypeEnglish":"HEALTH_FACILITY","email":"cc10006860@cc.dghs.gov.bd","phone":"0174952751"},
{"division":"Dhaka","district":"Narsingdi","upazila":"Narsingdi","union":"Hajipur","A2IReference":"division=3&district=29&upazila=229","facilityNameBengali":"বাদারপুর সিসি - নরসিংদী সদর","facilityNameEnglish":"Badarpur Cc - Narsingdi Sadar","facilityTypeBengali":"কমিউনিটি ক্লিনিক","facilityTypeEnglish":"HEALTH_FACILITY","email":"cc10006861@cc.dghs.gov.bd","phone":"01917278312"},
{"division":"Dhaka","district":"Narsingdi","upazila":"Narsingdi","union":"Hajipur","A2IReference":"division=3&district=29&upazila=229","facilityNameBengali":"হাজিপুর সিসি - নরসিংদী সদর","facilityNameEnglish":"Hajipur Cc - Narsingdi Sadar","facilityTypeBengali":"কমিউনিটি ক্লিনিক","facilityTypeEnglish":"HEALTH_FACILITY","email":"cc10006862@cc.dghs.gov.bd","phone":"01926150848"},
{"division":"Dhaka","district":"Narsingdi","upazila":"Narsingdi","union":"Kanthalia","A2IReference":"division=3&district=29&upazila=229","facilityNameBengali":"দাউকাদি সিসি - নরসিংদী সদর","facilityNameEnglish":"Daukadi Cc - Narsingdi Sadar","facilityTypeBengali":"কমিউনিটি ক্লিনিক","facilityTypeEnglish":"HEALTH_FACILITY","email":"cc10006863@cc.dghs.gov.bd","phone":"01914361436"},
{"division":"Dhaka","district":"Narsingdi","upazila":"Narsingdi","union":"Kanthalia","A2IReference":"division=3&district=29&upazila=229","facilityNameBengali":"খামারদি সিসি - নরসিংদী সদর","facilityNameEnglish":"Khamardi Cc - Narsingdi Sadar","facilityTypeBengali":"কমিউনিটি ক্লিনিক","facilityTypeEnglish":"HEALTH_FACILITY","email":"cc10006864@cc.dghs.gov.bd","phone":"01726913068"},
{"division":"Dhaka","district":"Narsingdi","upazila":"Narsingdi","union":"Karimpur","A2IReference":"division=3&district=29&upazila=229","facilityNameBengali":"পঞ্চবতি সিসি - নরসিংদী সদর","facilityNameEnglish":"Panchabati Cc - Narsingdi Sadar","facilityTypeBengali":"কমিউনিটি ক্লিনিক","facilityTypeEnglish":"HEALTH_FACILITY","email":"cc10006865@cc.dghs.gov.bd","phone":"01726075450"},
{"division":"Dhaka","district":"Narsingdi","upazila":"Narsingdi","union":"Karimpur","A2IReference":"division=3&district=29&upazila=229","facilityNameBengali":"রাসুলপুর সিসি - নরসিংদী সদর","facilityNameEnglish":"Rasulpur Cc - Narsingdi Sadar","facilityTypeBengali":"কমিউনিটি ক্লিনিক","facilityTypeEnglish":"HEALTH_FACILITY","email":"cc10006866@cc.dghs.gov.bd","phone":"01974920321"},
{"division":"Dhaka","district":"Narsingdi","upazila":"Narsingdi","union":"Karimpur","A2IReference":"division=3&district=29&upazila=229","facilityNameBengali":"শ্রীনগর মধ্যপাড়া সিসি - নরসিংদী সদর","facilityNameEnglish":"Sreenagar Madhyapara Cc - Narsingdi Sadar","facilityTypeBengali":"কমিউনিটি ক্লিনিক","facilityTypeEnglish":"HEALTH_FACILITY","email":"cc10006867@cc.dghs.gov.bd","phone":"01913153223"},
{"division":"Dhaka","district":"Narsingdi","upazila":"Narsingdi","union":"Mahishasura","A2IReference":"division=3&district=29&upazila=229","facilityNameBengali":"বালুচর সিসি - নরসিংদী সদর","facilityNameEnglish":"Baluchar Cc - Narsingdi Sadar","facilityTypeBengali":"কমিউনিটি ক্লিনিক","facilityTypeEnglish":"HEALTH_FACILITY","email":"cc10006868@cc.dghs.gov.bd","phone":"01675788144"},
{"division":"Dhaka","district":"Narsingdi","upazila":"Narsingdi","union":"Mahishasura","A2IReference":"division=3&district=29&upazila=229","facilityNameBengali":"চান্দেরপাড়া সিসি - নরসিংদী সদর","facilityNameEnglish":"Chanderpara Cc - Narsingdi Sadar","facilityTypeBengali":"কমিউনিটি ক্লিনিক","facilityTypeEnglish":"HEALTH_FACILITY","email":"cc10006869@cc.dghs.gov.bd","phone":"01712508717"},
{"division":"Dhaka","district":"Narsingdi","upazila":"Narsingdi","union":"Mahishasura","A2IReference":"division=3&district=29&upazila=229","facilityNameBengali":"দরিগাজিরগাঁও সিসি - নরসিংদী সদর","facilityNameEnglish":"Dorigazirgaon Cc - Narsingdi Sadar","facilityTypeBengali":"কমিউনিটি ক্লিনিক","facilityTypeEnglish":"HEALTH_FACILITY","email":"cc10006870@cc.dghs.gov.bd","phone":"01917677441"},
{"division":"Dhaka","district":"Narsingdi","upazila":"Narsingdi","union":"Mahishasura","A2IReference":"division=3&district=29&upazila=229","facilityNameBengali":"কোটালিচর সিসি - নরসিংদী সদর","facilityNameEnglish":"Kotalichor(bilpar) Cc - Narsingdi Sadar","facilityTypeBengali":"কমিউনিটি ক্লিনিক","facilityTypeEnglish":"HEALTH_FACILITY","email":"cc10006871@cc.dghs.gov.bd","phone":"01932469056"},
{"division":"Dhaka","district":"Narsingdi","upazila":"Narsingdi","union":"Mahishasura","A2IReference":"division=3&district=29&upazila=229","facilityNameBengali":"মহিষাসুরাগ্রাম সিসি - নরসিংদী সদর","facilityNameEnglish":"Mahishashuragram Cc - Narsingdi Sadar","facilityTypeBengali":"কমিউনিটি ক্লিনিক","facilityTypeEnglish":"HEALTH_FACILITY","email":"cc10006872@cc.dghs.gov.bd","phone":"01930731121"},
{"division":"Dhaka","district":"Narsingdi","upazila":"Narsingdi","union":"Meher Para","A2IReference":"division=3&district=29&upazila=229","facilityNameBengali":"মেহেরপুরা সিসি - নরসিংদী সদর","facilityNameEnglish":"Meherpara Cc - Narsingdi Sadar","facilityTypeBengali":"কমিউনিটি ক্লিনিক","facilityTypeEnglish":"HEALTH_FACILITY","email":"cc10006873@cc.dghs.gov.bd","phone":"01913271278"},
{"division":"Dhaka","district":"Narsingdi","upazila":"Narsingdi","union":"Meher Para","A2IReference":"division=3&district=29&upazila=229","facilityNameBengali":"সর্পনিগৈর সিসি - নরসিংদী সদর","facilityNameEnglish":"Sbarpanigair Cc - Narsingdi Sadar","facilityTypeBengali":"কমিউনিটি ক্লিনিক","facilityTypeEnglish":"HEALTH_FACILITY","email":"cc10006874@cc.dghs.gov.bd","phone":"01196179612"},
{"division":"Dhaka","district":"Narsingdi","upazila":"Narsingdi","union":"Nazarpur","A2IReference":"division=3&district=29&upazila=229","facilityNameBengali":"ছাগরিয়াপারা - নরসিংদী সদর","facilityNameEnglish":"Chhagriyapara Cc - Narsingdi Sadar","facilityTypeBengali":"কমিউনিটি ক্লিনিক","facilityTypeEnglish":"HEALTH_FACILITY","email":"cc10006875@cc.dghs.gov.bd","phone":"01945717848"},
{"division":"Dhaka","district":"Narsingdi","upazila":"Narsingdi","union":"Nazarpur","A2IReference":"division=3&district=29&upazila=229","facilityNameBengali":"দিলারপুর - নরসিংদী সদর","facilityNameEnglish":"Dilarpur (alipur School Cc) - Narsingdi Sadar","facilityTypeBengali":"কমিউনিটি ক্লিনিক","facilityTypeEnglish":"HEALTH_FACILITY","email":"cc10006876@cc.dghs.gov.bd","phone":"01981807643"},
{"division":"Dhaka","district":"Narsingdi","upazila":"Narsingdi","union":"Nazarpur","A2IReference":"division=3&district=29&upazila=229","facilityNameBengali":"দিলারপুর ঈদগাহ - নরসিংদী সদর","facilityNameEnglish":"Dilarpur Eidgah Cc - Narsingdi Sadar","facilityTypeBengali":"কমিউনিটি ক্লিনিক","facilityTypeEnglish":"HEALTH_FACILITY","email":"cc10006877@cc.dghs.gov.bd","phone":"01884606135"},
{"division":"Dhaka","district":"Narsingdi","upazila":"Narsingdi","union":"Nazarpur","A2IReference":"division=3&district=29&upazila=229","facilityNameBengali":"জামালিয়াকান্দি - নরসিংদী সদর","facilityNameEnglish":"Jamaliyakandi Cc - Narsingdi Sadar","facilityTypeBengali":"কমিউনিটি ক্লিনিক","facilityTypeEnglish":"HEALTH_FACILITY","email":"cc10006878@cc.dghs.gov.bd","phone":"01906477092"},
{"division":"Dhaka","district":"Narsingdi","upazila":"Narsingdi","union":"Paikar Char","A2IReference":"division=3&district=29&upazila=229","facilityNameBengali":"নর্থ চর বাশানিয়া - নরসিংদী সদর","facilityNameEnglish":"North Char Bashania Cc. Narsingdi Sadar","facilityTypeBengali":"কমিউনিটি ক্লিনিক","facilityTypeEnglish":"HEALTH_FACILITY","email":"cc10006879@cc.dghs.gov.bd","phone":"01717357621"},
{"division":"Dhaka","district":"Narsingdi","upazila":"Narsingdi","union":"Panchdona","A2IReference":"division=3&district=29&upazila=229","facilityNameBengali":"ভাতপারা সিসি - নরসিংদী সদর","facilityNameEnglish":"Bhatpara Cc - Narsingdi Sadar","facilityTypeBengali":"কমিউনিটি ক্লিনিক","facilityTypeEnglish":"HEALTH_FACILITY","email":"cc10006880@cc.dghs.gov.bd","phone":"01914536450"},
{"division":"Dhaka","district":"Narsingdi","upazila":"Narsingdi","union":"Panchdona","A2IReference":"division=3&district=29&upazila=229","facilityNameBengali":"কাকশিয়া - নরসিংদী সদর","facilityNameEnglish":"Kakshiya Cc - Narsingdi Sadar","facilityTypeBengali":"কমিউনিটি ক্লিনিক","facilityTypeEnglish":"HEALTH_FACILITY","email":"cc10006881@cc.dghs.gov.bd","phone":"01861349096"},
{"division":"Dhaka","district":"Narsingdi","upazila":"Narsingdi","union":"Silmandi","A2IReference":"division=3&district=29&upazila=229","facilityNameBengali":"শেখেরচর সিসি - নরসিংদী সদর","facilityNameEnglish":"Shekherchar Cc - Narsingdi Sadar","facilityTypeBengali":"কমিউনিটি ক্লিনিক","facilityTypeEnglish":"HEALTH_FACILITY","email":"cc10006882@cc.dghs.gov.bd","phone":"01717358766"},
{"division":"Dhaka","district":"Narsingdi","upazila":"Narsingdi","union":"Silmandi","A2IReference":"division=3&district=29&upazila=229","facilityNameBengali":"শিলামান্দি সিসি - নরসিংদী সদর","facilityNameEnglish":"Shilmandi Cc - Narsingdi Sadar","facilityTypeBengali":"কমিউনিটি ক্লিনিক","facilityTypeEnglish":"HEALTH_FACILITY","email":"cc10006883@cc.dghs.gov.bd","phone":"01940563431"},
{"division":"Dhaka","district":"Narsingdi","upazila":"Narsingdi","union":"Amdia","A2IReference":"division=3&district=29&upazila=229","facilityNameBengali":"আলোকবালি ইউনিয়ন সেন্টার","facilityNameEnglish":"Alokbali Union Centre","facilityTypeBengali":"ইউনিয়্ন স্বাস্থ্য কেন্দ্র","facilityTypeEnglish":"HEALTH_FACILITY","email":"u10015520@union.dghs.gov.bd","phone":""},
{"division":"Dhaka","district":"Narsingdi","upazila":"Narsingdi","union":"","A2IReference":"division=3&district=29&upazila=229","facilityNameBengali":"চরদিঘলদি ইউনিয়ন সেন্টার","facilityNameEnglish":"Chardighaldi Union Centre","facilityTypeBengali":"ইউনিয়্ন স্বাস্থ্য কেন্দ্র","facilityTypeEnglish":"HEALTH_FACILITY","email":"u10015521@union.dghs.gov.bd","phone":""},
{"division":"Dhaka","district":"Narsingdi","upazila":"Narsingdi","union":"","A2IReference":"division=3&district=29&upazila=229","facilityNameBengali":"চিনিসপুর ইউনিয়ন সেন্টার","facilityNameEnglish":"Chinishpur Union Centre","facilityTypeBengali":"ইউনিয়্ন স্বাস্থ্য কেন্দ্র","facilityTypeEnglish":"HEALTH_FACILITY","email":"u10015522@union.dghs.gov.bd","phone":""},
{"division":"Dhaka","district":"Narsingdi","upazila":"Narsingdi","union":"","A2IReference":"division=3&district=29&upazila=229","facilityNameBengali":"নজরপুর ইউনিয়ন সেন্টার","facilityNameEnglish":"Nazarpur Union Centre","facilityTypeBengali":"ইউনিয়্ন স্বাস্থ্য কেন্দ্র","facilityTypeEnglish":"HEALTH_FACILITY","email":"u10015523@union.dghs.gov.bd","phone":""},
{"division":"Dhaka","district":"Narsingdi","upazila":"Narsingdi","union":"","A2IReference":"division=3&district=29&upazila=229","facilityNameBengali":"নুরালপুর ইউনিয়ন সেন্টার","facilityNameEnglish":"Nuralpur Union Centre","facilityTypeBengali":"ইউনিয়্ন স্বাস্থ্য কেন্দ্র","facilityTypeEnglish":"HEALTH_FACILITY","email":"u10015524@union.dghs.gov.bd","phone":""},
{"division":"Dhaka","district":"Narsingdi","upazila":"Narsingdi","union":"Paikar Char","A2IReference":"division=3&district=29&upazila=229","facilityNameBengali":"পাইকারচর ইউনিয়ন সেন্টার","facilityNameEnglish":"Paikar Char Union Centre","facilityTypeBengali":"ইউনিয়্ন স্বাস্থ্য কেন্দ্র","facilityTypeEnglish":"HEALTH_FACILITY","email":"u10015525@union.dghs.gov.bd","phone":""},
{"division":"Dhaka","district":"Narsingdi","upazila":"Narsingdi","union":"Meher Para","A2IReference":"division=3&district=29&upazila=229","facilityNameBengali":"শিলামান্দি ইউনিয়ন সেন্টার","facilityNameEnglish":"Silmandi Union Centre","facilityTypeBengali":"ইউনিয়্ন স্বাস্থ্য কেন্দ্র","facilityTypeEnglish":"HEALTH_FACILITY","email":"u10015526@union.dghs.gov.bd","phone":""},
{"division":"Dhaka","district":"Narsingdi","upazila":"Narsingdi","union":"Alokbali","A2IReference":"division=3&district=29&upazila=229","facilityNameBengali":"কাযিরকান্দি সিসি - নরসিংদী সদর","facilityNameEnglish":"Kazir Kandi Cc - Narsingdi Sadar","facilityTypeBengali":"কমিউনিটি ক্লিনিক","facilityTypeEnglish":"HEALTH_FACILITY","email":"cc10018891@cc.dghs.gov.bd","phone":""},
{"division":"Dhaka","district":"Narsingdi","upazila":"Narsingdi","union":"","A2IReference":"division=3&district=29&upazila=229","facilityNameBengali":"ব্র্যাক (বিএইচপি) - নরসিংদী সদর","facilityNameEnglish":"BRAC (BHP) -Narsingdi Sadar","facilityTypeBengali":"এনজিও হাসপাতাল / ক্লিনিক","facilityTypeEnglish":"HEALTH_FACILITY","email":"","phone":"01721495481"},
{"division":"Dhaka","district":"Narsingdi","upazila":"Narsingdi","union":"","A2IReference":"division=3&district=29&upazila=229","facilityNameBengali":"বাংলাদেশ রেড ক্রিসেন্ট সোসাইটি - নরসিংদী সদর","facilityNameEnglish":"Bangladesh Red Crescent Society-Narsingdi Sadar","facilityTypeBengali":"এনজিও হাসপাতাল / ক্লিনিক","facilityTypeEnglish":"HEALTH_FACILITY","email":"","phone":"01718064921"},
{"division":"Dhaka","district":"Narsingdi","upazila":"Narsingdi","union":"","A2IReference":"division=3&district=29&upazila=229","facilityNameBengali":"মেরি স্টোপস সিসি - নরসিংদী সদর","facilityNameEnglish":"Marie Stops-Narsingdi Sadar","facilityTypeBengali":"এনজিও হাসপাতাল / ক্লিনিক","facilityTypeEnglish":"HEALTH_FACILITY","email":"","phone":"01711620086"},
{"division":"Dhaka","district":"Narsingdi","upazila":"Narsingdi","union":"","A2IReference":"division=3&district=29&upazila=229","facilityNameBengali":"বাংলাদেশ এসোসিয়েশন ফর অফ প্রেভেনশন সেপটিক এবোরশন","facilityNameEnglish":"Bangladesh Association for Prevention of Septic Abortion -Narsingdi Sadar","facilityTypeBengali":"এনজিও হাসপাতাল / ক্লিনিক","facilityTypeEnglish":"HEALTH_FACILITY","email":"","phone":"01711710063"},
{"division":"Dhaka","district":"Narsingdi","upazila":"Narsingdi","union":"Chinishpur","A2IReference":"division=3&district=29&upazila=229","facilityNameBengali":"ব্র্যাক (বিএইচপি)- নরসিংদী সদর","facilityNameEnglish":"BRAC (BHP)-Narsingdi Sadar","facilityTypeBengali":"এনজিও হাসপাতাল / ক্লিনিক","facilityTypeEnglish":"HEALTH_FACILITY","email":"","phone":"01711979394"},
{"division":"Dhaka","district":"Narsingdi","upazila":"Narsingdi","union":"","A2IReference":"division=3&district=29&upazila=229","facilityNameBengali":"ওয়েলকাম হসপিটাল - নরসিংদী সদর","facilityNameEnglish":"Welcome Hospital Pvt.-Narsingdi Sadar","facilityTypeBengali":"বেসরকারী হাসপাতাল / ক্লিনিক","facilityTypeEnglish":"HEALTH_FACILITY","email":"","phone":"01717201621"},
{"division":"Dhaka","district":"Narsingdi","upazila":"Narsingdi","union":"","A2IReference":"division=3&district=29&upazila=229","facilityNameBengali":"মডার্ন ক্লিনিক - নরসিংদী সদর","facilityNameEnglish":"Narsingdi Modern Clinic-Narsingdi Sadar","facilityTypeBengali":"বেসরকারী হাসপাতাল / ক্লিনিক","facilityTypeEnglish":"HEALTH_FACILITY","email":"","phone":"01711811535"},
{"division":"Dhaka","district":"Narsingdi","upazila":"Narsingdi","union":"","A2IReference":"division=3&district=29&upazila=229","facilityNameBengali":"প্রাইম জেনারেল হসপিটাল - নরসিংদী সদর","facilityNameEnglish":"Prime General Hospital-Narsingdi Sadar","facilityTypeBengali":"বেসরকারী হাসপাতাল / ক্লিনিক","facilityTypeEnglish":"HEALTH_FACILITY","email":"","phone":"01716626769"},
{"division":"Dhaka","district":"Narsingdi","upazila":"Narsingdi","union":"","A2IReference":"division=3&district=29&upazila=229","facilityNameBengali":"নরসিংদী জেনারেল হসপিটাল - নরসিংদী সদর","facilityNameEnglish":"Narsingdhi General Hospital-Narsingdi Sadar","facilityTypeBengali":"বেসরকারী হাসপাতাল / ক্লিনিক","facilityTypeEnglish":"HEALTH_FACILITY","email":"","phone":"01711320536"},
{"division":"Dhaka","district":"Narsingdi","upazila":"Narsingdi","union":"","A2IReference":"division=3&district=29&upazila=229","facilityNameBengali":"মুক্তি জেনারেল হসপিটাল - নরসিংদী সদর","facilityNameEnglish":"Mukti General Hospital-Narsingdi Sadar","facilityTypeBengali":"বেসরকারী হাসপাতাল / ক্লিনিক","facilityTypeEnglish":"HEALTH_FACILITY","email":"","phone":"01712581171"},
{"division":"Dhaka","district":"Narsingdi","upazila":"Narsingdi","union":"","A2IReference":"division=3&district=29&upazila=229","facilityNameBengali":"ন্যাশনাল জেনারেল চাইল্ড হসপিটাল - নরসিংদী সদর","facilityNameEnglish":"National General Child Hospital-Narsingdi Sadar","facilityTypeBengali":"বেসরকারী হাসপাতাল / ক্লিনিক","facilityTypeEnglish":"HEALTH_FACILITY","email":"","phone":"01714688017"},
{"division":"Dhaka","district":"Narsingdi","upazila":"Narsingdi","union":"","A2IReference":"division=3&district=29&upazila=229","facilityNameBengali":"ইবিএ প্রাইভেট হসপিটাল - নরসিংদী সদর","facilityNameEnglish":"EBA Private Hospital-Narsingdi Sadar","facilityTypeBengali":"বেসরকারী হাসপাতাল / ক্লিনিক","facilityTypeEnglish":"HEALTH_FACILITY","email":"","phone":"01711816903"},
{"division":"Dhaka","district":"Narsingdi","upazila":"Narsingdi","union":"","A2IReference":"division=3&district=29&upazila=229","facilityNameBengali":"হলি লাইফ জেনারেল হসপিটাল - নরসিংদী সদর","facilityNameEnglish":"Holy Life General Hospital-Narsingdi Sadar","facilityTypeBengali":"বেসরকারী হাসপাতাল / ক্লিনিক","facilityTypeEnglish":"HEALTH_FACILITY","email":"","phone":"01812247800"},
{"division":"Dhaka","district":"Narsingdi","upazila":"Narsingdi","union":"","A2IReference":"division=3&district=29&upazila=229","facilityNameBengali":"সুফিয়া পিভিটি. হসপিটাল - নরসিংদী সদর","facilityNameEnglish":"Sufia Pvt. Hospital-Narsingdi Sadar","facilityTypeBengali":"বেসরকারী হাসপাতাল / ক্লিনিক","facilityTypeEnglish":"HEALTH_FACILITY","email":"","phone":"01711681816"},
{"division":"Dhaka","district":"Narsingdi","upazila":"Narsingdi","union":"","A2IReference":"division=3&district=29&upazila=229","facilityNameBengali":"মাধোভি জেনারেল হসপিটাল - নরসিংদী সদর","facilityNameEnglish":"Madhavi General Hospital-Narsingdi Sadar","facilityTypeBengali":"বেসরকারী হাসপাতাল / ক্লিনিক","facilityTypeEnglish":"HEALTH_FACILITY","email":"","phone":"01722163479"},
{"division":"Dhaka","district":"Narsingdi","upazila":"Narsingdi","union":"","A2IReference":"division=3&district=29&upazila=229","facilityNameBengali":"পলি ক্লিনিক এন্ড আই কেয়ার সেন্টার - নরসিংদী সদর","facilityNameEnglish":"Poli Clinic and Eye Care Center-Narsingdi Sadar","facilityTypeBengali":"বেসরকারী হাসপাতাল / ক্লিনিক","facilityTypeEnglish":"HEALTH_FACILITY","email":"","phone":"01711445138"},
{"division":"Dhaka","district":"Narsingdi","upazila":"Narsingdi","union":"","A2IReference":"division=3&district=29&upazila=229","facilityNameBengali":"আলফালাহা পিপলস প্রাইভেট হসপিটাল - নরসিংদী সদর","facilityNameEnglish":"Alfalaha Pipals Prikate Hospital-Narsingdi Sadar","facilityTypeBengali":"বেসরকারী হাসপাতাল / ক্লিনিক","facilityTypeEnglish":"HEALTH_FACILITY","email":"","phone":"01712272942"},
{"division":"Dhaka","district":"Narsingdi","upazila":"Narsingdi","union":"","A2IReference":"division=3&district=29&upazila=229","facilityNameBengali":"এপোলো হসপিটাল - নরসিংদী সদর","facilityNameEnglish":"Apollo Hospital-Narsingdi Sadar","facilityTypeBengali":"বেসরকারী হাসপাতাল / ক্লিনিক","facilityTypeEnglish":"HEALTH_FACILITY","email":"","phone":"01711574245"},
{"division":"Dhaka","district":"Narsingdi","upazila":"Narsingdi","union":"","A2IReference":"division=3&district=29&upazila=229","facilityNameBengali":"পিপলস প্রাইভেট হসপিটাল - নরসিংদী সদর","facilityNameEnglish":"People's Pvt. Hospital-Narsingdi Sadar","facilityTypeBengali":"বেসরকারী হাসপাতাল / ক্লিনিক","facilityTypeEnglish":"HEALTH_FACILITY","email":"","phone":"01191312445"},
{"division":"Dhaka","district":"Narsingdi","upazila":"Narsingdi","union":"","A2IReference":"division=3&district=29&upazila=229","facilityNameBengali":"মিতা নার্সিং হোম - নরসিংদী সদর","facilityNameEnglish":"Mita Nursing Home-Narsingdi Sadar","facilityTypeBengali":"বেসরকারী হাসপাতাল / ক্লিনিক","facilityTypeEnglish":"HEALTH_FACILITY","email":"","phone":"01711634265"},
{"division":"Dhaka","district":"Narsingdi","upazila":"Narsingdi","union":"","A2IReference":"division=3&district=29&upazila=229","facilityNameBengali":"হলি ক্রিসেন্ট হসপিটাল - নরসিংদী সদর","facilityNameEnglish":"Holly Cricent Hospital-Narsingdi Sadar","facilityTypeBengali":"বেসরকারী হাসপাতাল / ক্লিনিক","facilityTypeEnglish":"HEALTH_FACILITY","email":"","phone":"01716270730"},
{"division":"Dhaka","district":"Narsingdi","upazila":"Narsingdi","union":"","A2IReference":"division=3&district=29&upazila=229","facilityNameBengali":"ফেইথ জেনারেল হসপিটাল - নরসিংদী সদর","facilityNameEnglish":"Faith General Hospital-Narsingdi Sadar","facilityTypeBengali":"বেসরকারী হাসপাতাল / ক্লিনিক","facilityTypeEnglish":"HEALTH_FACILITY","email":"","phone":"01712104546"},
{"division":"Dhaka","district":"Narsingdi","upazila":"Narsingdi","union":"","A2IReference":"division=3&district=29&upazila=229","facilityNameBengali":"প্রাইম জেনারেল হসপিটাল - নরসিংদী সদর","facilityNameEnglish":"Prime General Hospital-Narsingdi Sadar-2","facilityTypeBengali":"বেসরকারী হাসপাতাল / ক্লিনিক","facilityTypeEnglish":"HEALTH_FACILITY","email":"","phone":"01711586350"},
{"division":"Dhaka","district":"Narsingdi","upazila":"Narsingdi","union":"","A2IReference":"division=3&district=29&upazila=229","facilityNameBengali":"মাদার অ্যান্ড চাইল্ড ওয়েলফেয়ার সেন্টার (এমসিডব্লিওসি) নরসিংদী সদর","facilityNameEnglish":"Mother & Child Welfare Centre (MCWC) Narsingdi Sadar","facilityTypeBengali":"মা ও শিশু কল্যান কেন্দ্র","facilityTypeEnglish":"HEALTH_FACILITY","email":"","phone":""},
{"division":"Dhaka","district":"Narsingdi","upazila":"Narsingdi","union":"","A2IReference":"division=3&district=29&upazila=229","facilityNameBengali":"ঢাকা প্রগ্রেসসিভ লায়ন্স আই হসপিটাল - নরসিংদী সদর","facilityNameEnglish":"Dhaka Progressive Lions Eye Hospital","facilityTypeBengali":"বিশেষায়িত হাসপাতাল","facilityTypeEnglish":"HEALTH_FACILITY","email":"dplehnbd101@gmail.com","phone":"01742248555"},
{"division":"Dhaka","district":"Narsingdi","upazila":"Narsingdi","union":"Silmandi","A2IReference":"division=3&district=29&upazila=229","facilityNameBengali":"বাঘহাটা টেক পাড়া সিসি - নরসিংদী সদর","facilityNameEnglish":"Baghhata take para CC - Narsingdi Sadar","facilityTypeBengali":"কমিউনিটি ক্লিনিক","facilityTypeEnglish":"HEALTH_FACILITY","email":"cc10023625@cc.dghs.gov.bd","phone":""},
{"division":"Dhaka","district":"Narsingdi","upazila":"Narsingdi","union":"Mahishasura","A2IReference":"division=3&district=29&upazila=229","facilityNameBengali":"ডঃ নুরুজামান খোকন সিসি - নরসিংদী সদর","facilityNameEnglish":"Dr. Nuruzzaman Khokon CC - Narsingdi Sadar","facilityTypeBengali":"কমিউনিটি ক্লিনিক","facilityTypeEnglish":"HEALTH_FACILITY","email":"cc10024892@cc.dghs.gov.bd","phone":"01731904481"},
{"division":"Rangpur","district":"Kurigram","upazila":"Kurigram Sadar","union":"Urban Ward No-02","A2IReference":"division=6&district=55&upazila=417","facilityNameBengali":"কুড়িগ্রাম (সদর) উপজেলা হেল্‌থ অফিস","facilityNameEnglish":"Kurigram (Sadar) Upazila Health office","facilityTypeBengali":"উপজেলা পর্যায়ের অফিস","facilityTypeEnglish":"HEALTH_FACILITY","email":"kurigramsadar@uhfpo.dghs.gov.bd","phone":"01710868407"},
{"division":"Rangpur","district":"Kurigram","upazila":"Kurigram Sadar","union":"Punchgachhi","A2IReference":"division=6&district=55&upazila=417","facilityNameBengali":"পাঁচগাছি (এউএইচএন্ডএফডবলিওসি)","facilityNameEnglish":"Pangachi Uh&fwc","facilityTypeBengali":"ইউনিয়ন স্বাস্থ্য ও পরিবার কল্যাণ কেন্দ্র","facilityTypeEnglish":"HEALTH_FACILITY","email":"pangachi@uhfwc.dghs.gov.bd","phone":""},
{"division":"Rangpur","district":"Kurigram","upazila":"Kurigram Sadar","union":"Urban Ward No-05","A2IReference":"division=6&district=55&upazila=417","facilityNameBengali":"কুড়িগ্রাম সিভিল সার্জন অফিস","facilityNameEnglish":"Kurigram Civil Surgeon Office","facilityTypeBengali":"জেলা পর্যায়ের অফিস","facilityTypeEnglish":"HEALTH_FACILITY","email":"kurigram@cs.dghs.gov.bd","phone":"01711109078"},
{"division":"Rangpur","district":"Kurigram","upazila":"Kurigram Sadar","union":"","A2IReference":"division=6&district=55&upazila=417","facilityNameBengali":"কুড়িগ্রাম জেলা হসপিটাল","facilityNameEnglish":"Kurigram District Hospital","facilityTypeBengali":"জেলা হাসপাতাল","facilityTypeEnglish":"HEALTH_FACILITY","email":"kurigram@hospi.dghs.gov.bd","phone":"01713200322"},
{"division":"Rangpur","district":"Kurigram","upazila":"Kurigram Sadar","union":"","A2IReference":"division=6&district=55&upazila=417","facilityNameBengali":"কুড়িগ্রাম চেস্ট ডিসিস ক্লিনিক","facilityNameEnglish":"Kurigram Chest Disease Clinic","facilityTypeBengali":"বক্ষব্যাধি ক্লিনিক","facilityTypeEnglish":"HEALTH_FACILITY","email":"kurigram@tc.dghs.gov.bd","phone":"01718658967"},
{"division":"Rangpur","district":"Kurigram","upazila":"Kurigram Sadar","union":"Belgachha","A2IReference":"division=6&district=55&upazila=417","facilityNameBengali":"চিলাপাড়া সিসি- কুড়িগ্রাম সদর","facilityNameEnglish":"Chilapara Cc","facilityTypeBengali":"কমিউনিটি ক্লিনিক","facilityTypeEnglish":"HEALTH_FACILITY","email":"cc10011516@cc.dghs.gov.bd","phone":"01925861050"},
{"division":"Rangpur","district":"Kurigram","upazila":"Kurigram Sadar","union":"Belgachha","A2IReference":"division=6&district=55&upazila=417","facilityNameBengali":"পলাশবাড়ী সিসি- কুড়িগ্রাম সদর","facilityNameEnglish":"Palashbari Cc","facilityTypeBengali":"কমিউনিটি ক্লিনিক","facilityTypeEnglish":"HEALTH_FACILITY","email":"cc10011517@cc.dghs.gov.bd","phone":"01718519393"},
{"division":"Rangpur","district":"Kurigram","upazila":"Kurigram Sadar","union":"Bhogdanga","A2IReference":"division=6&district=55&upazila=417","facilityNameBengali":"বাসুরভিটা সিসি- কুড়িগ্রাম সদর","facilityNameEnglish":"Basurvita Cc","facilityTypeBengali":"কমিউনিটি ক্লিনিক","facilityTypeEnglish":"HEALTH_FACILITY","email":"cc10011518@cc.dghs.gov.bd","phone":"01737130809"},
{"division":"Rangpur","district":"Kurigram","upazila":"Kurigram Sadar","union":"Bhogdanga","A2IReference":"division=6&district=55&upazila=417","facilityNameBengali":"মাধবরাম সিসি- কুড়িগ্রাম সদর","facilityNameEnglish":"Madhabram Cc","facilityTypeBengali":"কমিউনিটি ক্লিনিক","facilityTypeEnglish":"HEALTH_FACILITY","email":"cc10011519@cc.dghs.gov.bd","phone":" 1712933300"},
{"division":"Rangpur","district":"Kurigram","upazila":"Kurigram Sadar","union":"Bhogdanga","A2IReference":"division=6&district=55&upazila=417","facilityNameBengali":"উত্তর কুমারপুর সিসি- কুড়িগ্রাম সদর","facilityNameEnglish":"Uttor Kumarpur Cc","facilityTypeBengali":"কমিউনিটি ক্লিনিক","facilityTypeEnglish":"HEALTH_FACILITY","email":"cc10011520@cc.dghs.gov.bd","phone":"01764455159"},
{"division":"Rangpur","district":"Kurigram","upazila":"Kurigram Sadar","union":"Bhogdanga","A2IReference":"division=6&district=55&upazila=417","facilityNameBengali":"পারামালি সিসি- কুড়িগ্রাম সদর","facilityNameEnglish":"Paramali Cc","facilityTypeBengali":"কমিউনিটি ক্লিনিক","facilityTypeEnglish":"HEALTH_FACILITY","email":"cc10011521@cc.dghs.gov.bd","phone":"01723797946"},
{"division":"Rangpur","district":"Kurigram","upazila":"Kurigram Sadar","union":"Ghogadaha","A2IReference":"division=6&district=55&upazila=417","facilityNameBengali":"কাছিছার সিসি- কুড়িগ্রাম সদর","facilityNameEnglish":"Kachichar Cc","facilityTypeBengali":"কমিউনিটি ক্লিনিক","facilityTypeEnglish":"HEALTH_FACILITY","email":"cc10011522@cc.dghs.gov.bd","phone":"01714655451"},
{"division":"Rangpur","district":"Kurigram","upazila":"Kurigram Sadar","union":"Ghogadaha","A2IReference":"division=6&district=55&upazila=417","facilityNameBengali":"লাকশির খামার সিসি- কুড়িগ্রাম সদর","facilityNameEnglish":"Lakshir Khamar Cc","facilityTypeBengali":"কমিউনিটি ক্লিনিক","facilityTypeEnglish":"HEALTH_FACILITY","email":"cc10011523@cc.dghs.gov.bd","phone":"01723340477"},
{"division":"Rangpur","district":"Kurigram","upazila":"Kurigram Sadar","union":"Ghogadaha","A2IReference":"division=6&district=55&upazila=417","facilityNameBengali":"রাসুলপুর সিসি- কুড়িগ্রাম সদর","facilityNameEnglish":"Rasulpur Cc","facilityTypeBengali":"কমিউনিটি ক্লিনিক","facilityTypeEnglish":"HEALTH_FACILITY","email":"cc10011524@cc.dghs.gov.bd","phone":"01714655451"},
{"division":"Rangpur","district":"Kurigram","upazila":"Kurigram Sadar","union":"Holokhana","A2IReference":"division=6&district=55&upazila=417","facilityNameBengali":"লাকশিখান্ত সিসি- কুড়িগ্রাম সদর","facilityNameEnglish":"Lakshikanto Cc","facilityTypeBengali":"কমিউনিটি ক্লিনিক","facilityTypeEnglish":"HEALTH_FACILITY","email":"cc10011525@cc.dghs.gov.bd","phone":"01723588725"},
{"division":"Rangpur","district":"Kurigram","upazila":"Kurigram Sadar","union":"Holokhana","A2IReference":"division=6&district=55&upazila=417","facilityNameBengali":"হলোখানা সিসি- কুড়িগ্রাম সদর","facilityNameEnglish":"Halokhana Cc","facilityTypeBengali":"কমিউনিটি ক্লিনিক","facilityTypeEnglish":"HEALTH_FACILITY","email":"cc10011526@cc.dghs.gov.bd","phone":"01746445629"},
{"division":"Rangpur","district":"Kurigram","upazila":"Kurigram Sadar","union":"Holokhana","A2IReference":"division=6&district=55&upazila=417","facilityNameBengali":"ভেরভেরী সিসি- কুড়িগ্রাম সদর","facilityNameEnglish":"Ververi Cc","facilityTypeBengali":"কমিউনিটি ক্লিনিক","facilityTypeEnglish":"HEALTH_FACILITY","email":"cc10011527@cc.dghs.gov.bd","phone":"01716310428"},
{"division":"Rangpur","district":"Kurigram","upazila":"Kurigram Sadar","union":"Jatrapur","A2IReference":"division=6&district=55&upazila=417","facilityNameBengali":"ঘনেশ্যামপুর সিসি- কুড়িগ্রাম সদর","facilityNameEnglish":"Ghaneshyampur Cc","facilityTypeBengali":"কমিউনিটি ক্লিনিক","facilityTypeEnglish":"HEALTH_FACILITY","email":"cc10011528@cc.dghs.gov.bd","phone":"017214654"},
{"division":"Rangpur","district":"Kurigram","upazila":"Kurigram Sadar","union":"Kanthalbari","A2IReference":"division=6&district=55&upazila=417","facilityNameBengali":"আধগ্রাম সিসি- কুড়িগ্রাম সদর","facilityNameEnglish":"Adhgram Cc","facilityTypeBengali":"কমিউনিটি ক্লিনিক","facilityTypeEnglish":"HEALTH_FACILITY","email":"cc10011529@cc.dghs.gov.bd","phone":"01712725205"},
{"division":"Rangpur","district":"Kurigram","upazila":"Kurigram Sadar","union":"Kanthalbari","A2IReference":"division=6&district=55&upazila=417","facilityNameBengali":"জোতগোবরধন সিসি- কুড়িগ্রাম সদর","facilityNameEnglish":"Jotgobardhan Cc","facilityTypeBengali":"কমিউনিটি ক্লিনিক","facilityTypeEnglish":"HEALTH_FACILITY","email":"cc10011530@cc.dghs.gov.bd","phone":"01722373526"},
{"division":"Rangpur","district":"Kurigram","upazila":"Kurigram Sadar","union":"Kanthalbari","A2IReference":"division=6&district=55&upazila=417","facilityNameBengali":"খালিসা কালোয়া সিসি- কুড়িগ্রাম সদর","facilityNameEnglish":"Khalisa Kalowa Cc","facilityTypeBengali":"কমিউনিটি ক্লিনিক","facilityTypeEnglish":"HEALTH_FACILITY","email":"cc10011531@cc.dghs.gov.bd","phone":"02147483647"},
{"division":"Rangpur","district":"Kurigram","upazila":"Kurigram Sadar","union":"Mogalbachha","A2IReference":"division=6&district=55&upazila=417","facilityNameBengali":"উত্তর সিতাইঝার সিসি- কুড়িগ্রাম সদর","facilityNameEnglish":"Uttor Sitaijhar Cc","facilityTypeBengali":"কমিউনিটি ক্লিনিক","facilityTypeEnglish":"HEALTH_FACILITY","email":"cc10011532@cc.dghs.gov.bd","phone":"01721764827"},
{"division":"Rangpur","district":"Kurigram","upazila":"Kurigram Sadar","union":"Mogalbachha","A2IReference":"division=6&district=55&upazila=417","facilityNameBengali":"দক্ষিন সিতাইঝার সিসি- কুড়িগ্রাম সদর","facilityNameEnglish":"Dakhin Sitaijhar Cc","facilityTypeBengali":"কমিউনিটি ক্লিনিক","facilityTypeEnglish":"HEALTH_FACILITY","email":"cc10011533@cc.dghs.gov.bd","phone":"01714558275"},
{"division":"Rangpur","district":"Kurigram","upazila":"Kurigram Sadar","union":"Punchgachhi","A2IReference":"division=6&district=55&upazila=417","facilityNameBengali":"গোবিন্দাপুর সিসি- কুড়িগ্রাম সদর","facilityNameEnglish":"Gobindapur Cc","facilityTypeBengali":"কমিউনিটি ক্লিনিক","facilityTypeEnglish":"HEALTH_FACILITY","email":"cc10011534@cc.dghs.gov.bd","phone":"01717624150"},
{"division":"Rangpur","district":"Kurigram","upazila":"Kurigram Sadar","union":"Punchgachhi","A2IReference":"division=6&district=55&upazila=417","facilityNameBengali":"শুলকুর বাজার সিসি- কুড়িগ্রাম সদর","facilityNameEnglish":"Shulkur Bazar Cc","facilityTypeBengali":"কমিউনিটি ক্লিনিক","facilityTypeEnglish":"HEALTH_FACILITY","email":"cc10011535@cc.dghs.gov.bd","phone":"01923004451"},
{"division":"Rangpur","district":"Kurigram","upazila":"Kurigram Sadar","union":"Punchgachhi","A2IReference":"division=6&district=55&upazila=417","facilityNameBengali":"সিতাইঝার সিসি- কুড়িগ্রাম সদর","facilityNameEnglish":"Sitaijhar Cc","facilityTypeBengali":"কমিউনিটি ক্লিনিক","facilityTypeEnglish":"HEALTH_FACILITY","email":"cc10011536@cc.dghs.gov.bd","phone":"01728655858"},
{"division":"Rangpur","district":"Kurigram","upazila":"Kurigram Sadar","union":"Holokhana","A2IReference":"division=6&district=55&upazila=417","facilityNameBengali":"হলোখানা সিসি- কুড়িগ্রাম সদর","facilityNameEnglish":"Holokhana Union Centre","facilityTypeBengali":"ইউনিয়্ন স্বাস্থ্য কেন্দ্র","facilityTypeEnglish":"HEALTH_FACILITY","email":"u10016726@union.dghs.gov.bd","phone":""},
{"division":"Rangpur","district":"Kurigram","upazila":"Kurigram Sadar","union":"Jatrapur","A2IReference":"division=6&district=55&upazila=417","facilityNameBengali":"জাত্তারাপুর সিসি- কুড়িগ্রাম সদর","facilityNameEnglish":"Jattarapur Union Centre","facilityTypeBengali":"ইউনিয়্ন স্বাস্থ্য কেন্দ্র","facilityTypeEnglish":"HEALTH_FACILITY","email":"u10016727@union.dghs.gov.bd","phone":""},
{"division":"Rangpur","district":"Kurigram","upazila":"Kurigram Sadar","union":"Kanthalbari","A2IReference":"division=6&district=55&upazila=417","facilityNameBengali":"খাতালবাড়ী সিসি- কুড়িগ্রাম সদর","facilityNameEnglish":"Khatalbari Union Centre","facilityTypeBengali":"ইউনিয়্ন স্বাস্থ্য কেন্দ্র","facilityTypeEnglish":"HEALTH_FACILITY","email":"u10016728@union.dghs.gov.bd","phone":""},
{"division":"Rangpur","district":"Kurigram","upazila":"Kurigram Sadar","union":"Mogalbachha","A2IReference":"division=6&district=55&upazila=417","facilityNameBengali":"মঘুলবাসা সিসি- কুড়িগ্রাম সদর","facilityNameEnglish":"Mogulbasha Union Centre","facilityTypeBengali":"ইউনিয়্ন স্বাস্থ্য কেন্দ্র","facilityTypeEnglish":"HEALTH_FACILITY","email":"u10016729@union.dghs.gov.bd","phone":""},
{"division":"Rangpur","district":"Kurigram","upazila":"Kurigram Sadar","union":"Bhogdanga","A2IReference":"division=6&district=55&upazila=417","facilityNameBengali":"ভগদাঙ্গা সিসি- কুড়িগ্রাম সদর","facilityNameEnglish":"Vogdanga Union Centre","facilityTypeBengali":"ইউনিয়্ন স্বাস্থ্য কেন্দ্র","facilityTypeEnglish":"HEALTH_FACILITY","email":"u10016730@union.dghs.gov.bd","phone":""},
{"division":"Rangpur","district":"Kurigram","upazila":"Kurigram Sadar","union":"Bhogdanga","A2IReference":"division=6&district=55&upazila=417","facilityNameBengali":"চর বরাইবাড়ী সিসি- কুড়িগ্রাম সদর","facilityNameEnglish":"Char Boraibari Cc","facilityTypeBengali":"কমিউনিটি ক্লিনিক","facilityTypeEnglish":"HEALTH_FACILITY","email":"cc10018007@cc.dghs.gov.bd","phone":"01764884557"},
{"division":"Rangpur","district":"Kurigram","upazila":"Kurigram Sadar","union":"Kanthalbari","A2IReference":"division=6&district=55&upazila=417","facilityNameBengali":"খালিশা যালফারা সিসি- কুড়িগ্রাম সদর","facilityNameEnglish":"Khalisha Zalfara Cc","facilityTypeBengali":"কমিউনিটি ক্লিনিক","facilityTypeEnglish":"HEALTH_FACILITY","email":"cc10018139@cc.dghs.gov.bd","phone":"01718971370"},
{"division":"Rangpur","district":"Kurigram","upazila":"Kurigram Sadar","union":"Mogalbachha","A2IReference":"division=6&district=55&upazila=417","facilityNameBengali":"ভেলাকোপা সিসি- কুড়িগ্রাম সদর","facilityNameEnglish":"Velakopa CC","facilityTypeBengali":"কমিউনিটি ক্লিনিক","facilityTypeEnglish":"HEALTH_FACILITY","email":"cc10018140@cc.dghs.gov.bd","phone":"01718971370"},
{"division":"Rangpur","district":"Kurigram","upazila":"Kurigram Sadar","union":"Bhogdanga","A2IReference":"division=6&district=55&upazila=417","facilityNameBengali":"কাছিচর তেলিপারা)সিসি- কুড়িগ্রাম সদর","facilityNameEnglish":"Kachichar(telipara) Cc","facilityTypeBengali":"কমিউনিটি ক্লিনিক","facilityTypeEnglish":"HEALTH_FACILITY","email":"cc10018142@cc.dghs.gov.bd","phone":"01718971370"},
{"division":"Rangpur","district":"Kurigram","upazila":"Kurigram Sadar","union":"Ghogadaha","A2IReference":"division=6&district=55&upazila=417","facilityNameBengali":"মরাতরি সিসি- কুড়িগ্রাম সদর","facilityNameEnglish":"Moratari Cc","facilityTypeBengali":"কমিউনিটি ক্লিনিক","facilityTypeEnglish":"HEALTH_FACILITY","email":"cc10018150@cc.dghs.gov.bd","phone":"01718971370"},
{"division":"Rangpur","district":"Kurigram","upazila":"Kurigram Sadar","union":"Holokhana","A2IReference":"division=6&district=55&upazila=417","facilityNameBengali":"হিমেরকুটি সিসি- কুড়িগ্রাম সদর","facilityNameEnglish":"Himerkuti Cc","facilityTypeBengali":"কমিউনিটি ক্লিনিক","facilityTypeEnglish":"HEALTH_FACILITY","email":"cc10018152@cc.dghs.gov.bd","phone":"01718971370"},
{"division":"Rangpur","district":"Kurigram","upazila":"Kurigram Sadar","union":"Jatrapur","A2IReference":"division=6&district=55&upazila=417","facilityNameBengali":"পিপুলবাড়ী সিসি- কুড়িগ্রাম সদর","facilityNameEnglish":"Pipul Bari CC","facilityTypeBengali":"কমিউনিটি ক্লিনিক","facilityTypeEnglish":"HEALTH_FACILITY","email":"cc10018153@cc.dghs.gov.bd","phone":"01713728843"},
{"division":"Rangpur","district":"Kurigram","upazila":"Kurigram Sadar","union":"Bhogdanga","A2IReference":"division=6&district=55&upazila=417","facilityNameBengali":"মধ্য কুমরপুর সিসি- কুড়িগ্রাম সদর","facilityNameEnglish":"Madhya Kumorpur Cc","facilityTypeBengali":"কমিউনিটি ক্লিনিক","facilityTypeEnglish":"HEALTH_FACILITY","email":"cc10018154@cc.dghs.gov.bd","phone":"01718971370"},
{"division":"Rangpur","district":"Kurigram","upazila":"Kurigram Sadar","union":"Punchgachhi","A2IReference":"division=6&district=55&upazila=417","facilityNameBengali":"কদমতলা সিসি- কুড়িগ্রাম সদর","facilityNameEnglish":"Kadomtola Cc","facilityTypeBengali":"কমিউনিটি ক্লিনিক","facilityTypeEnglish":"HEALTH_FACILITY","email":"cc10018155@cc.dghs.gov.bd","phone":"01718971370"},
{"division":"Rangpur","district":"Kurigram","upazila":"Kurigram Sadar","union":"Mogalbachha","A2IReference":"division=6&district=55&upazila=417","facilityNameBengali":"চর কিষ্ণপুর সিসি- কুড়িগ্রাম সদর","facilityNameEnglish":"Char Kisnopur Cc","facilityTypeBengali":"কমিউনিটি ক্লিনিক","facilityTypeEnglish":"HEALTH_FACILITY","email":"cc10018227@cc.dghs.gov.bd","phone":"01718971370"},
{"division":"Rangpur","district":"Kurigram","upazila":"Kurigram Sadar","union":"Belgachha","A2IReference":"division=6&district=55&upazila=417","facilityNameBengali":"পুর্ব কল্যাণ সিসি- কুড়িগ্রাম সদর","facilityNameEnglish":"Purbo Kollan Cc","facilityTypeBengali":"কমিউনিটি ক্লিনিক","facilityTypeEnglish":"HEALTH_FACILITY","email":"cc10018375@cc.dghs.gov.bd","phone":"01718971370"},
{"division":"Rangpur","district":"Kurigram","upazila":"Kurigram Sadar","union":"Jatrapur","A2IReference":"division=6&district=55&upazila=417","facilityNameBengali":"পার্বতীপুর সিসি- কুড়িগ্রাম সদর","facilityNameEnglish":"Parbotipur Cc","facilityTypeBengali":"কমিউনিটি ক্লিনিক","facilityTypeEnglish":"HEALTH_FACILITY","email":"cc10019040@cc.dghs.gov.bd","phone":"01718971370"},
{"division":"Rangpur","district":"Kurigram","upazila":"Kurigram Sadar","union":"Jatrapur","A2IReference":"division=6&district=55&upazila=417","facilityNameBengali":"তেরে দেস হোমস ফাউন্ডেশন - কুড়িগ্রাম সদর","facilityNameEnglish":"Terre Des Hommes Foundation-Kurigram Sadar","facilityTypeBengali":"এনজিও হাসপাতাল / ক্লিনিক","facilityTypeEnglish":"HEALTH_FACILITY","email":"","phone":"01734022316"},
{"division":"Rangpur","district":"Kurigram","upazila":"Kurigram Sadar","union":"Kanthalbari","A2IReference":"division=6&district=55&upazila=417","facilityNameBengali":"আরডিআরএস বাংলাদেশ -কুড়িগ্রাম সদর","facilityNameEnglish":"RDRS Bangladesh-Kurigram Sadar","facilityTypeBengali":"এনজিও হাসপাতাল / ক্লিনিক","facilityTypeEnglish":"HEALTH_FACILITY","email":"","phone":"01712315867"},
{"division":"Rangpur","district":"Kurigram","upazila":"Kurigram Sadar","union":"Belgachha","A2IReference":"division=6&district=55&upazila=417","facilityNameBengali":"ব্র্যাক (বিএইচপি) - কুড়িগ্রাম সদর","facilityNameEnglish":"BRAC (BHP) -Kurigram Sadar","facilityTypeBengali":"এনজিও হাসপাতাল / ক্লিনিক","facilityTypeEnglish":"HEALTH_FACILITY","email":"","phone":"01721417574"},
{"division":"Rangpur","district":"Kurigram","upazila":"Kurigram Sadar","union":"","A2IReference":"division=6&district=55&upazila=417","facilityNameBengali":"পারিবাইক স্বাস্থ্য ক্লিনিক - কুড়িগ্রাম সদর","facilityNameEnglish":"Paribaik Shastho Clinic-Kurigram Sadar","facilityTypeBengali":"এনজিও হাসপাতাল / ক্লিনিক","facilityTypeEnglish":"HEALTH_FACILITY","email":"","phone":"01718319215"},
{"division":"Rangpur","district":"Kurigram","upazila":"Kurigram Sadar","union":"","A2IReference":"division=6&district=55&upazila=417","facilityNameBengali":"আরডিআরএস বাংলাদেশ - কুড়িগ্রাম সদর – ২ !","facilityNameEnglish":"RDRS Bangladesh-Kurigram Sadar-2 !","facilityTypeBengali":"এনজিও হাসপাতাল / ক্লিনিক","facilityTypeEnglish":"HEALTH_FACILITY","email":"","phone":"01725344597"},
{"division":"Rangpur","district":"Kurigram","upazila":"Kurigram Sadar","union":"","A2IReference":"division=6&district=55&upazila=417","facilityNameBengali":"ছিন্ন মুকুল - কুড়িগ্রাম সদর","facilityNameEnglish":"Chinno Mukul-Kurigram Sadar","facilityTypeBengali":"এনজিও হাসপাতাল / ক্লিনিক","facilityTypeEnglish":"HEALTH_FACILITY","email":"","phone":"01718312951"},
{"division":"Rangpur","district":"Kurigram","upazila":"Kurigram Sadar","union":"Jatrapur","A2IReference":"division=6&district=55&upazila=417","facilityNameBengali":"তেরে দেস হোমস ফাউন্ডেশন - কুড়িগ্রাম সদর -২ (!)","facilityNameEnglish":"Terre Des Hommes Foundation-Kurigram Sadar-2 (!)","facilityTypeBengali":"এনজিও হাসপাতাল / ক্লিনিক","facilityTypeEnglish":"HEALTH_FACILITY","email":"","phone":"01734022316"},
{"division":"Rangpur","district":"Kurigram","upazila":"Kurigram Sadar","union":"","A2IReference":"division=6&district=55&upazila=417","facilityNameBengali":"সেবা ক্লিনিক - কুড়িগ্রাম সদর","facilityNameEnglish":"Sheba Clinic-Kurigram Sadar","facilityTypeBengali":"বেসরকারী হাসপাতাল / ক্লিনিক","facilityTypeEnglish":"HEALTH_FACILITY","email":"","phone":"01714052116"},
{"division":"Rangpur","district":"Kurigram","upazila":"Kurigram Sadar","union":"","A2IReference":"division=6&district=55&upazila=417","facilityNameBengali":"খান ক্লিনিক - কুড়িগ্রাম সদর","facilityNameEnglish":"Khan Clinic-Kurigram Sadar","facilityTypeBengali":"বেসরকারী হাসপাতাল / ক্লিনিক","facilityTypeEnglish":"HEALTH_FACILITY","email":"","phone":"01714230285"},
{"division":"Rangpur","district":"Kurigram","upazila":"Kurigram Sadar","union":"","A2IReference":"division=6&district=55&upazila=417","facilityNameBengali":"ধারলা ক্লিনিক - কুড়িগ্রাম সদর","facilityNameEnglish":"Dharla clinic-Kurigram Sadar","facilityTypeBengali":"বেসরকারী হাসপাতাল / ক্লিনিক","facilityTypeEnglish":"HEALTH_FACILITY","email":"","phone":"01718697932"},
{"division":"Rangpur","district":"Kurigram","upazila":"Kurigram Sadar","union":"","A2IReference":"division=6&district=55&upazila=417","facilityNameBengali":"কুড়িগ্রাম ক্লিনিক - কুড়িগ্রাম সদর","facilityNameEnglish":"Kurigram clinic-Kurigram Sadar","facilityTypeBengali":"বেসরকারী হাসপাতাল / ক্লিনিক","facilityTypeEnglish":"HEALTH_FACILITY","email":"","phone":"01712687317"},
{"division":"Rangpur","district":"Kurigram","upazila":"Kurigram Sadar","union":"","A2IReference":"division=6&district=55&upazila=417","facilityNameBengali":"মাদার অ্যান্ড চাইল্ড ওয়েলফেয়ার (এমসিডবলিওসি)","facilityNameEnglish":"Mother & Child Welfare Centre (MCWC) Kurigram Sadar","facilityTypeBengali":"মা ও শিশু কল্যান কেন্দ্র","facilityTypeEnglish":"HEALTH_FACILITY","email":"","phone":""},
{"division":"Rangpur","district":"Kurigram","upazila":"Kurigram Sadar","union":"Urban Ward No-03","A2IReference":"division=6&district=55&upazila=417","facilityNameBengali":"জেলা ফ্যামিলি প্লানিং অফিস কুড়িগ্রাম","facilityNameEnglish":"District Family Planing Office Kurigram","facilityTypeBengali":"জেলা পর্যায়ের অফিস","facilityTypeEnglish":"HEALTH_FACILITY","email":"dfpokuri@gmail.com","phone":""},
{"division":"Rangpur","district":"Kurigram","upazila":"Kurigram Sadar","union":"Holokhana","A2IReference":"division=6&district=55&upazila=417","facilityNameBengali":"ইউনিয়ন হেলথ অ্যান্ড ফ্যামিলি ওয়েলফেয়ার সেন্টার (এউএইচএন্ডএফডবলিওসি) হলোখানা কুড়িগ্রাম সদর কুড়িগ্রাম","facilityNameEnglish":"UH&FWC Holokhana","facilityTypeBengali":"ইউনিয়ন স্বাস্থ্য ও পরিবার কল্যাণ কেন্দ্র","facilityTypeEnglish":"HEALTH_FACILITY","email":"","phone":"01728052261"},
{"division":"Rangpur","district":"Kurigram","upazila":"Kurigram Sadar","union":"Urban Ward No-01","A2IReference":"division=6&district=55&upazila=417","facilityNameBengali":"উপজেলা ফ্যামিলি প্লানিং অফিস সদর কুড়িগ্রাম","facilityNameEnglish":"Upazila Family Planning Office Sadar Kurigram","facilityTypeBengali":"উপজেলা পর্যায়ের অফিস","facilityTypeEnglish":"HEALTH_FACILITY","email":"","phone":"01714004225"}
]
